edapi/__init__.py
edapi/constants.py
edapi/edapi.py
edapi/utils.py
edapi/types/__init__.py
edapi/types/types.py
edapi/types/api_types/__init__.py
edapi/types/api_types/category.py
edapi/types/api_types/content.py
edapi/types/api_types/course.py
edapi/types/api_types/lesson.py
edapi/types/api_types/marking.py
edapi/types/api_types/thread.py
edapi/types/api_types/user.py
edapi/types/api_types/endpoints/__init__.py
edapi/types/api_types/endpoints/activity.py
edapi/types/api_types/endpoints/files.py
edapi/types/api_types/endpoints/lessons.py
edapi/types/api_types/endpoints/markings.py
edapi/types/api_types/endpoints/threads.py
edapi/types/api_types/endpoints/user.py
edapiwl-0.0.3.dist-info/LICENSE
edapiwl-0.0.3.dist-info/METADATA
edapiwl-0.0.3.dist-info/WHEEL
edapiwl-0.0.3.dist-info/top_level.txt
edapiwl-0.0.3.dist-info/RECORD
