Metadata-Version: 2.1
Name: edapiwl
Version: 0.0.3
Summary: A modified version of edapi, an unofficial integration of the Ed API with Python
Project-URL: Homepage, https://github.com/trevmoy/edapiwl
Classifier: License :: OSI Approved :: GNU General Public License v3 (GPLv3)
Requires-Python: >=3.9
License-File: LICENSE
Requires-Dist: requests
Requires-Dist: python-dotenv
Requires-Dist: beautifulsoup4
